{"version":1,"resource":"vscode-remote://wsl%2Bubuntu-20.04/home/paolo/develop/cursodeintroduccionareact/src/index.js","entries":[{"id":"bWNe.js","timestamp":1670303715495},{"id":"D09N.js","timestamp":1670351956448},{"id":"qfg4.js","timestamp":1670351995618},{"id":"OehB.js","timestamp":1670385157941},{"id":"yTyu.js","timestamp":1670385940561},{"id":"UlVX.js","timestamp":1670386257531},{"id":"QlXG.js","timestamp":1670386596191},{"id":"od01.js","timestamp":1670449188007},{"id":"SS1F.js","timestamp":1670451062517},{"id":"PyIm.js","timestamp":1670451142127},{"id":"LtJ0.js","timestamp":1670451160407},{"id":"3Crg.js","source":"undoRedo.source","timestamp":1670451167117},{"id":"hYiO.js","timestamp":1670451328657},{"id":"czSD.js","timestamp":1670470254026},{"id":"Mx6K.js","timestamp":1670470516006}]}