{"version":1,"resource":"vscode-remote://wsl%2Bubuntu-20.04/home/paolo/soyHenry/henryChallengue/2022-12-17-yaaaps/prueba.js","entries":[{"id":"e11l.js","timestamp":1671327337819},{"id":"tzlo.js","source":"undoRedo.source","timestamp":1671327370469},{"id":"tmaP.js","timestamp":1671327532359},{"id":"Ydan.js","timestamp":1671327546079},{"id":"vxkv.js","timestamp":1671327563719},{"id":"Qo0V.js","source":"undoRedo.source","timestamp":1671327569639},{"id":"sxwE.js","timestamp":1671327617079},{"id":"ef3k.js","timestamp":1671327651249},{"id":"FakD.js","timestamp":1671327669529},{"id":"qc3j.js","timestamp":1671327679689},{"id":"ZSuV.js","timestamp":1671327702929},{"id":"nCwe.js","timestamp":1671328358629},{"id":"6AdU.js","timestamp":1671328382619},{"id":"O58R.js","timestamp":1671328397349},{"id":"jHcL.js","timestamp":1671328435979},{"id":"iNPF.js","timestamp":1671328450289},{"id":"6RjF.js","timestamp":1671328493469},{"id":"0IlZ.js","timestamp":1671328518919},{"id":"7Qtj.js","timestamp":1671328559839},{"id":"UOid.js","timestamp":1671328582099},{"id":"ReQY.js","timestamp":1671328632999},{"id":"fgOW.js","timestamp":1671328799719},{"id":"3xnz.js","timestamp":1671328812549},{"id":"vCf2.js","timestamp":1671328827469},{"id":"tdU5.js","timestamp":1671328859429},{"id":"Ucxb.js","timestamp":1671328950759},{"id":"f2UK.js","timestamp":1671329070709},{"id":"opHJ.js","timestamp":1671329219629},{"id":"DcP0.js","timestamp":1671329290319},{"id":"07TV.js","timestamp":1671329700099},{"id":"CibW.js","timestamp":1671329817659},{"id":"IF7w.js","timestamp":1671329872129},{"id":"1ahV.js","timestamp":1671330196799},{"id":"MiLX.js","timestamp":1671330233819},{"id":"ywQ7.js","timestamp":1671330255639},{"id":"ZjhM.js","timestamp":1671330274779},{"id":"3FlR.js","timestamp":1671330358089},{"id":"CIlg.js","timestamp":1671330395529},{"id":"IVsD.js","timestamp":1671330410619},{"id":"6y0B.js","timestamp":1671330484759},{"id":"q7Xj.js","timestamp":1671330526639},{"id":"xhER.js","timestamp":1671330643599},{"id":"VNDE.js","timestamp":1671330654799},{"id":"oXGR.js","timestamp":1671330667049},{"id":"PJtm.js","timestamp":1671330749689},{"id":"nsj7.js","timestamp":1671331951889},{"id":"Lc4T.js","timestamp":1671331986859},{"id":"IAof.js","timestamp":1671332007209},{"id":"iSDB.js","source":"undoRedo.source","timestamp":1671332015599},{"id":"BVjD.js","timestamp":1671332919399}]}